dash_server_file_browser/__init__.py
dash_server_file_browser/__version__.py
dash_server_file_browser/file_browser.py
dash_server_file_browser/util/__init__.py
dash_server_file_browser/util/filetype.py
dash_server_file_browser-0.2.0.dist-info/LICENSE
dash_server_file_browser-0.2.0.dist-info/METADATA
dash_server_file_browser-0.2.0.dist-info/WHEEL
dash_server_file_browser-0.2.0.dist-info/RECORD
