Metadata-Version: 2.3
Name: dash-server-file-browser
Version: 0.2.0
Summary: All-in-one file browser component for Dash applications based on Dash Bootstrap Components.
License: MIT
Keywords: dash,dash-bootstrap-components,file-browser
Author: Jannik Hinrichs
Author-email: Zoraiyo@outlook.de
Requires-Python: >=3.9, <4
Classifier: License :: OSI Approved :: MIT License
Classifier: Programming Language :: Python :: 3
Classifier: Framework :: Dash
Requires-Dist: dash (>=3.0.1,<4.0.0)
Requires-Dist: dash-bootstrap-components (>=2.0.0,<3.0.0)
Project-URL: Repository, https://github.com/Zoraiyo/dash-server-file-browser
Project-URL: issues, https://github.com/Zoraiyo/dash-server-file-browser/issues
